pyiks-0.4.1.dist-info/METADATA
pyiks-0.4.1.dist-info/WHEEL
pyiks-0.4.1.dist-info/licenses/COPYING
pyiks-0.4.1.dist-info/licenses/COPYING.LESSER
pyiks/__init__.py
pyiks/pyiks.cpython-314-darwin.so
pyiks-0.4.1.dist-info/RECORD
