Metadata-Version: 2.4
Name: pyiks
Version: 0.4.1
Classifier: Development Status :: 4 - Beta
Classifier: Intended Audience :: Developers
Classifier: License :: OSI Approved :: GNU Lesser General Public License v3 or later (LGPLv3+)
Classifier: Programming Language :: Rust
Classifier: Programming Language :: Python :: Implementation :: CPython
Classifier: Programming Language :: Python :: Implementation :: PyPy
Classifier: Topic :: File Formats
Classifier: Topic :: Internet :: XMPP
Classifier: Topic :: Software Development :: Libraries
Classifier: Topic :: Text Processing :: Markup :: XML
License-File: COPYING
License-File: COPYING.LESSER
Summary: A Python binding for the iksemel XML/XMPP library.
License-Expression: LGPL-3.0-or-later
Requires-Python: >=3.10
Project-URL: homepage, https://github.com/meduketto/iksemel-python
